[
  {"section": 56, "entry_eng": "In Lutsk -- 3", "entry_rus": "в Луцке -- 3", "content_category": "Information", "framing": "Generic / Neutral Language", "context": "In Lutsk -- 3"},
  {"section": 57, "entry_eng": "Military Attaché of the Embassy of the Federal Republic of Germany", "entry_rus": "военный атташе посольства ФРГ", "content_category": "Actors", "framing": "Institutional / Bureaucratic Lingo", "context": "Military Attaché of the Embassy of the Federal Republic of Germany"},
  {"section": 58, "entry_eng": "G. Schroeter", "entry_rus": "Г. Шретер", "content_category": "Actors", "framing": "Generic / Neutral Language", "context": "G. Schroeter"},
  {"section": 59, "entry_eng": "Air Attaché of the Embassy of the Federal Republic of Germany", "entry_rus": "военно-воздушный атташе посольства ФРГ", "content_category": "Actors", "framing": "Institutional / Bureaucratic Lingo", "context": "Air Attaché of the Embassy of the Federal Republic of Germany"},
  {"section": 60, "entry_eng": "G. Barakling", "entry_rus": "Г. Бараклинг", "content_category": "Actors", "framing": "Generic / Neutral Language", "context": "G. Barakling"},
  {"section": 61, "entry_eng": "Military Attaché staff member", "entry_rus": "сотрудник военного атташе этого посольства", "content_category": "Actors", "framing": "Institutional / Bureaucratic Lingo", "context": "Military Attaché staff member"},
  {"section": 62, "entry_eng": "P. Jürgens", "entry_rus": "П. Юргенс", "content_category": "Actors", "framing": "Generic / Neutral Language", "context": "P. Jürgens"},
  {"section": 63, "entry_eng": "Arrived on October 12 of this year", "entry_rus": "с 12 октября с.г.", "content_category": "Time", "framing": "Generic / Neutral Language", "context": "Arrived on October 12 of this year"},
  {"section": 64, "entry_eng": "On a reconnaissance trip", "entry_rus": "разведывательная поездка", "content_category": "Actions", "framing": "Institutional / Bureaucratic Lingo", "context": "On a reconnaissance trip"},
  {"section": 65, "entry_eng": "on October 13", "entry_rus": "13 октября", "content_category": "Time", "framing": "Generic / Neutral Language", "context": "on October 13"},
  {"section": 66, "entry_eng": "[Scheduled] to depart for Lviv", "entry_rus": "убывают во Львов", "content_category": "Actions", "framing": "Generic / Neutral Language", "context": "[Scheduled] to depart for Lviv"},
  {"section": 67, "entry_eng": "In Kharkiv -- 2", "entry_rus": "в Харькове -- 2", "content_category": "Information", "framing": "Generic / Neutral Language", "context": "In Kharkiv -- 2"},
  {"section": 68, "entry_eng": "Military Attaché of the U.S. Embassy", "entry_rus": "военный атташе посольства США", "content_category": "Actors", "framing": "Institutional / Bureaucratic Lingo", "context": "Military Attaché of the U.S. Embassy"},
  {"section": 69, "entry_eng": "D. Halloran", "entry_rus": "Д. Холлоран", "content_category": "Actors", "framing": "Generic / Neutral Language", "context": "D. Halloran"},
  {"section": 70, "entry_eng": "Assistant to the Military Attaché", "entry_rus": "помощник военного атташе", "content_category": "Actors", "framing": "Institutional / Bureaucratic Lingo", "context": "Assistant to the Military Attaché"},
  {"section": 71, "entry_eng": "L. Mercer", "entry_rus": "Л. Мерсер", "content_category": "Actors", "framing": "Generic / Neutral Language", "context": "L. Mercer"},
  {"section": 72, "entry_eng": "Arrived October 11", "entry_rus": "с 11 октября с.г.", "content_category": "Time", "framing": "Generic / Neutral Language", "context": "Arrived October 11"},
  {"section": 73, "entry_eng": "On a reconnaissance trip", "entry_rus": "разведывательная поездка", "content_category": "Actions", "framing": "Institutional / Bureaucratic Lingo", "context": "On a reconnaissance trip"},
  {"section": 74, "entry_eng": "Departed for Moscow on October 12", "entry_rus": "12 октября убыли", "content_category": "Actions", "framing": "Action-Focused Language", "context": "Departed for Moscow on October 12"},
  {"section": 75, "entry_eng": "for Moscow", "entry_rus": "в Москву", "content_category": "Places", "framing": "Generic / Neutral Language", "context": "for Moscow"},
  {"section": 76, "entry_eng": "In Rivne", "entry_rus": "в Ровно", "content_category": "Places", "framing": "Generic / Neutral Language", "context": "In Rivne"},
  {"section": 77, "entry_eng": "Attaché of the Nigerian Embassy", "entry_rus": "атташе посольства Нигерии", "content_category": "Actors", "framing": "Institutional / Bureaucratic Lingo", "context": "Attaché of the Nigerian Embassy"},
  {"section": 78, "entry_eng": "S. Ako", "entry_rus": "С. Ако", "content_category": "Actors", "framing": "Generic / Neutral Language", "context": "S. Ako"},
  {"section": 79, "entry_eng": "Arrived at the High-Voltage Equipment Plant of the USSR Ministry of Electrical Industry", "entry_rus": "прибыл на завод высоковольтной аппаратуры Минэлектротехпрома СССР", "content_category": "Actions", "framing": "Action-Focused Language", "context": "Arrived at the High-Voltage Equipment Plant of the USSR Ministry of Electrical Industry"},
  {"section": 80, "entry_eng": "For equipment acceptance", "entry_rus": "для приёмки оборудования", "content_category": "Actions", "framing": "Generic / Neutral Language", "context": "For equipment acceptance"},
  {"section": 81, "entry_eng": "In addition, in Kharkiv, there were present", "entry_rus": "кроме того, в Харькове находятся", "content_category": "Information", "framing": "Generic / Neutral Language", "context": "In addition, in Kharkiv, there were present"},
  {"section": 82, "entry_eng": "Second Secretaries of the Embassy of the People's Republic of China", "entry_rus": "вторые секретари посольства КНР", "content_category": "Actors", "framing": "Institutional / Bureaucratic Lingo", "context": "Second Secretaries of the Embassy of the People's Republic of China"},
  {"section": 83, "entry_eng": "Dai Changshi", "entry_rus": "Дай Чанши", "content_category": "Actors", "framing": "Generic / Neutral Language", "context": "Dai Changshi"},
  {"section": 84, "entry_eng": "Du Zhongcheng", "entry_rus": "Ду Чжунчэн", "content_category": "Actors", "framing": "Generic / Neutral Language", "context": "Du Zhongcheng"},
  {"section": 85, "entry_eng": "On a familiarization visit", "entry_rus": "ознакомительная поездка", "content_category": "Actions", "framing": "Generic / Neutral Language", "context": "On a familiarization visit"},
  {"section": 86, "entry_eng": "Tourists — 1,470", "entry_rus": "туристов 1 470", "content_category": "Information", "framing": "Generic / Neutral Language", "context": "Tourists — 1,470"},
  {"section": 87, "entry_eng": "In Yalta — 886", "entry_rus": "в Ялте 886", "content_category": "Information", "framing": "Generic / Neutral Language", "context": "In Yalta — 886"},
  {"section": 88, "entry_eng": "Kyiv — 497", "entry_rus": "в Киеве 497", "content_category": "Information", "framing": "Generic / Neutral Language", "context": "Kyiv — 497"},
  {"section": 89, "entry_eng": "Lviv — 38", "entry_rus": "во Львове 38", "content_category": "Information", "framing": "Generic / Neutral Language", "context": "Lviv — 38"},
  {"section": 90, "entry_eng": "Odesa — 30", "entry_rus": "в Одессе 30", "content_category": "Information", "framing": "Generic / Neutral Language", "context": "Odesa — 30"},
  {"section": 91, "entry_eng": "Other cities — 19", "entry_rus": "в других городах 19", "content_category": "Information", "framing": "Generic / Neutral Language", "context": "Other cities — 19"},
  {"section": 92, "entry_eng": "From the U.S. — 55", "entry_rus": "из США 55", "content_category": "Information", "framing": "Generic / Neutral Language", "context": "From the U.S. — 55"},
  {"section": 93, "entry_eng": "U.K. — 16", "entry_rus": "из Англии 16", "content_category": "Information", "framing": "Generic / Neutral Language", "context": "U.K. — 16"},
  {"section": 94, "entry_eng": "FRG — 455", "entry_rus": "из ФРГ 455", "content_category": "Information", "framing": "Generic / Neutral Language", "context": "FRG — 455"},
  {"section": 95, "entry_eng": "Canada — 34", "entry_rus": "из Канады 34", "content_category": "Information", "framing": "Generic / Neutral Language", "context": "Canada — 34"}
]
