[
  {"section": 16, "entry_eng": "On Anti-Soviet Action", "entry_rus": "Об антисоветской акции", "content_category": "Events", "framing": "Ideological Framing (Discrediting)", "context": "On Anti-Soviet Action"},
  {"section": 17, "entry_eng": "in the USA", "entry_rus": "в США", "content_category": "Places", "framing": "Generic / Neutral Language", "context": "in the USA"},
  {"section": 18, "entry_eng": "According to information received by the KGB of the Ukrainian SSR", "entry_rus": "По полученным КГБ УССР данным", "content_category": "Information", "framing": "Institutional / Bureaucratic Lingo", "context": "According to information received by the KGB of the Ukrainian SSR"},
  {"section": 19, "entry_eng": "on October 9, 1983", "entry_rus": "9 октября 1983 г.", "content_category": "Time", "framing": "Generic / Neutral Language", "context": "on October 9, 1983"},
  {"section": 20, "entry_eng": "in a suburb of Washington (State of Maryland)", "entry_rus": "в пригороде Вашингтона (штат Мэриленд)", "content_category": "Places", "framing": "Generic / Neutral Language", "context": "in a suburb of Washington (State of Maryland)"},
  {"section": 21, "entry_eng": "a gathering organized [...] took place", "entry_rus": "состоялось организованное [...] сборище", "content_category": "Events", "framing": "Ideological Framing (Discrediting)", "context": "a gathering organized [...] took place"},
  {"section": 22, "entry_eng": "by the OUNites", "entry_rus": "оуновцами", "content_category": "Actors", "framing": "Ideological Framing (Discrediting)", "context": "by the OUNites"},
  {"section": 23, "entry_eng": "timed to coincide", "entry_rus": "приуроченное к", "content_category": "Context and Concepts", "framing": "Generic / Neutral Language", "context": "timed to coincide"},
  {"section": 24, "entry_eng": "with the laying of a \"monument\"", "entry_rus": "закладке \"монумента\"", "content_category": "Actions", "framing": "Ideological Framing (Discrediting)", "context": "with the laying of a \"monument\""},
  {"section": 25, "entry_eng": "in honor of the so-called \"Free Ukraine\"", "entry_rus": "в честь так называемой \"свободной Украины\"", "content_category": "Context and Concepts", "framing": "Ideological Framing (Discrediting)", "context": "in honor of the so-called \"Free Ukraine\""},
  {"section": 26, "entry_eng": "ringleaders", "entry_rus": "Главарями", "content_category": "Actors", "framing": "Ideological Framing (Discrediting)", "context": "ringleaders"},
  {"section": 27, "entry_eng": "of the foreign branches of the OUN", "entry_rus": "зарубежных ОУН", "content_category": "Actors", "framing": "Ideological Framing (Discrediting)", "context": "of the foreign branches of the OUN"},
  {"section": 28, "entry_eng": "conceived it as", "entry_rus": "он задуман как", "content_category": "Context and Concepts", "framing": "Generic / Neutral Language", "context": "conceived it as"},
  {"section": 29, "entry_eng": "\"monument-mausoleum to the fallen fighters for Ukraine's freedom and the victims of the artificial famine of 1932–1933\"", "entry_rus": "\"памятник-мавзолей павшим борцам за свободу Украины и жертвам искусственного голода 1932–1933 годов\"", "content_category": "Context and Concepts", "framing": "Ideological Framing (Discrediting)", "context": "\"monument-mausoleum to the fallen fighters for Ukraine's freedom and the victims of the artificial famine of 1932–1933\""},
  {"section": 30, "entry_eng": "It is planned that a museum will be established at its base", "entry_rus": "В его основании предполагается создать", "content_category": "Actions", "framing": "Generic / Neutral Language", "context": "It is planned that a museum will be established at its base"},
  {"section": 31, "entry_eng": "featuring an exhibition", "entry_rus": "музей с экспозицией", "content_category": "Places", "framing": "Generic / Neutral Language", "context": "featuring an exhibition"},
  {"section": 32, "entry_eng": "\"materials on the history of Ukrainians' struggle for a free Ukraine\"", "entry_rus": "\"материалов по истории борьбы украинцев за свободную Украину\"", "content_category": "Documents", "framing": "Ideological Framing (Discrediting)", "context": "\"materials on the history of Ukrainians' struggle for a free Ukraine\""},
  {"section": 33, "entry_eng": "It is assumed", "entry_rus": "Предположительно", "content_category": "Context and Concepts", "framing": "Generic / Neutral Language", "context": "It is assumed"},
  {"section": 34, "entry_eng": "The estimated cost of constructing the \"monument\"", "entry_rus": "стоимость строительства \"монумента\"", "content_category": "Information", "framing": "Generic / Neutral Language", "context": "The estimated cost of constructing the \"monument\""},
  {"section": 35, "entry_eng": "height — more than 30 meters", "entry_rus": "высота — более 30 м", "content_category": "Information", "framing": "Generic / Neutral Language", "context": "height — more than 30 meters"},
  {"section": 36, "entry_eng": "is approximately $12 million", "entry_rus": "составит около 12 млн долларов", "content_category": "Information", "framing": "Generic / Neutral Language", "context": "is approximately $12 million"},
  {"section": 37, "entry_eng": "among OUNites", "entry_rus": "Среди оуновцев", "content_category": "Actors", "framing": "Ideological Framing (Discrediting)", "context": "among OUNites"},
  {"section": 38, "entry_eng": "Fundraising is being conducted [...] for its construction", "entry_rus": "проводится сбор пожертвований на его сооружение", "content_category": "Actions", "framing": "Action-Focused Language", "context": "Fundraising is being conducted [...] for its construction"},
  {"section": 39, "entry_eng": "This gathering", "entry_rus": "Указанному сборищу", "content_category": "Events", "framing": "Generic / Neutral Language", "context": "This gathering"},
  {"section": 40, "entry_eng": "was preceded [...] conducted", "entry_rus": "предшествовало проведённое", "content_category": "Actions", "framing": "Generic / Neutral Language", "context": "was preceded [...] conducted"},
  {"section": 41, "entry_eng": "on September 10 of this year", "entry_rus": "10 сентября с.г.", "content_category": "Time", "framing": "Generic / Neutral Language", "context": "on September 10 of this year"},
  {"section": 42, "entry_eng": "by representatives", "entry_rus": "представителями", "content_category": "Actors", "framing": "Generic / Neutral Language", "context": "by representatives"},
  {"section": 43, "entry_eng": "of the Ukrainian Catholic Church in the USA", "entry_rus": "украинской католической церкви в США", "content_category": "Actors", "framing": "Generic / Neutral Language", "context": "of the Ukrainian Catholic Church in the USA"},
  {"section": 44, "entry_eng": "by a \"blessing of the land\"", "entry_rus": "\"освящение земли\"", "content_category": "Actions", "framing": "Generic / Neutral Language", "context": "by a \"blessing of the land\""},
  {"section": 45, "entry_eng": "at the monument's construction site", "entry_rus": "на месте строительства \"монумента\"", "content_category": "Places", "framing": "Generic / Neutral Language", "context": "at the monument's construction site"},
  {"section": 46, "entry_eng": "The KGB of the USSR is informed", "entry_rus": "КГБ СССР известно", "content_category": "Information", "framing": "Institutional / Bureaucratic Lingo", "context": "The KGB of the USSR is informed"},
  {"section": 47, "entry_eng": "In the territory of the Ukrainian SSR", "entry_rus": "На территории Украинской ССР", "content_category": "Places", "framing": "Generic / Neutral Language", "context": "In the territory of the Ukrainian SSR"},
  {"section": 48, "entry_eng": "As of October 12, there were", "entry_rus": "12 октября находились", "content_category": "Time", "framing": "Generic / Neutral Language", "context": "As of October 12, there were"},
  {"section": 49, "entry_eng": "17,232 foreigners", "entry_rus": "17 232 иностранца", "content_category": "Information", "framing": "Generic / Neutral Language", "context": "17,232 foreigners"},
  {"section": 50, "entry_eng": "from capitalist and developing countries", "entry_rus": "из капиталистических и развивающихся стран", "content_category": "Context and Concepts", "framing": "Ideological Phrasing (Normalizing)", "context": "from capitalist and developing countries"},
  {"section": 51, "entry_eng": "Diplomats accredited in the USSR — 7", "entry_rus": "дипломатов, аккредитованных в СССР 7", "content_category": "Information", "framing": "Generic / Neutral Language", "context": "Diplomats accredited in the USSR — 7"},
  {"section": 52, "entry_eng": "In Kyiv", "entry_rus": "в Киеве", "content_category": "Places", "framing": "Generic / Neutral Language", "context": "In Kyiv"},
  {"section": 53, "entry_eng": "Newly appointed Ambassador of Canada to the USSR", "entry_rus": "вновь назначенный посол Канады в СССР", "content_category": "Actors", "framing": "Institutional / Bureaucratic Lingo", "context": "Newly appointed Ambassador of Canada to the USSR"},
  {"section": 54, "entry_eng": "P. Roberts", "entry_rus": "П. Робертс", "content_category": "Actors", "framing": "Generic / Neutral Language", "context": "P. Roberts"},
  {"section": 55, "entry_eng": "En route to Moscow", "entry_rus": "следует в Москву", "content_category": "Actions", "framing": "Generic / Neutral Language", "context": "En route to Moscow"}
]
